{
    "nombre_trabajador": "PORTEROS TORRES, ROSA CLONIRA",
    "puesto_trabajo": "LAVADO",
    "edad": 18,
    "experiencia": 200,
    "lugar_accidente": "",
    "hora_accidente": "13:50",
    "fecha_accidente": "2024-10-28",
    "lesion": "",
    "tipo_lesion": [
        0,
        0,
        0,
        0
    ],
    "lesionado_check": false,
    "sexo": "M",
    "descripcion_hechos": "",
    "imagenes": "[]",
    "id": "b21ca69d-e342-4a31-a078-86d67e0d9bb9",
    "valoracionHechos": "ALTA,MUY GRAVE,NO,NO,NO",
    "formas_accidente": "",
    "analisis_causas": "[[],[],[],[],[],[],[],[]]",
    "causas_accidente": "",
    "aplicar_accion": "[]"
}